dsc_toolkit/__init__.py
dsc_toolkit/cli.py
dsc_toolkit/plot_annotations_3d.py
dsc_toolkit/plot_annotations_georeferenced.py
dsc_toolkit/render_orthophoto.py
dsc_toolkit/utils/__init__.py
dsc_toolkit/utils/generic.py
dsc_toolkit/utils/geospatial.py
dsc_toolkit/utils/io.py
dsc_toolkit/utils/visuals.py
dsc_toolkit-1.0.3.dist-info/METADATA
dsc_toolkit-1.0.3.dist-info/WHEEL
dsc_toolkit-1.0.3.dist-info/entry_points.txt
dsc_toolkit-1.0.3.dist-info/licenses/LICENSE.txt
dsc_toolkit-1.0.3.dist-info/RECORD
