Metadata-Version: 2.4
Name: dsc-toolkit
Version: 1.0.3
Summary: DeepScenario Toolkit for visualizing and working with DeepScenario datasets
Project-URL: Homepage, https://app.deepscenario.com
Project-URL: Documentation, https://github.com/deepscenario/dsc-toolkit#readme
Project-URL: Repository, https://github.com/deepscenario/dsc-toolkit
Project-URL: Bug Tracker, https://github.com/deepscenario/dsc-toolkit/issues
Author-email: DeepScenario <info@deepscenario.com>
License-Expression: Apache-2.0
License-File: LICENSE.txt
Keywords: 3d,autonomous-driving,computer-vision,deepscenario,traffic,visualization
Classifier: Development Status :: 4 - Beta
Classifier: Intended Audience :: Developers
Classifier: Intended Audience :: Science/Research
Classifier: License :: OSI Approved :: Apache Software License
Classifier: Operating System :: OS Independent
Classifier: Programming Language :: Python :: 3
Classifier: Programming Language :: Python :: 3.10
Classifier: Programming Language :: Python :: 3.11
Classifier: Programming Language :: Python :: 3.12
Classifier: Topic :: Scientific/Engineering :: Visualization
Classifier: Topic :: Software Development :: Libraries :: Python Modules
Requires-Python: <4.0,>=3.10
Requires-Dist: folium<1,>=0.20
Requires-Dist: numpy<3.0,>=1.26
Requires-Dist: open3d<1.0,>=0.19
Requires-Dist: pandas<3.0,>=2.2
Requires-Dist: pyarrow<21.0,>=20.0
Requires-Dist: pyproj<4.0,>=3.6
Requires-Dist: rasterio<2.0,>=1.3
Requires-Dist: scipy<2.0,>=1.14
Requires-Dist: tqdm<5.0,>=4.66
Requires-Dist: vedo>=2025.5.3
